rtl/spi.sv
`timescale 1ns / 1ps
module spi_intf(
    input wr,clk,rst,ready,op_done,
    input [7:0] addr, din,
    output [7:0] dout,
    output reg cs, mosi,
    input miso,
    output reg done, err
);
reg [16:0] din_reg;  //// <- data 0:7 -> <- addr 0 : 7 -> <- op: wr / rd ->
reg [7:0] dout_reg;

integer count = 0;

typedef enum bit [2:0] {idle = 0, load = 1, check_op = 2, send_data = 3, read_data1 = 4, read_data2 = 5, error = 6, check_ready = 7} state_type;
state_type state = idle; 

always@(posedge clk) begin
    if(rst) begin
        state <= idle;
        count <= 0;
        cs <= 1'b1;
        mosi <= 1'b0; 
        err <= 1'b0;
        done <= 1'b0;
        dout_reg <= 0;
        din_reg <= 0;
    end
    else begin
        case(state)
            idle: begin
                cs    <= 1'b1;
                mosi  <= 1'b0;
                state <= load;
                err   <= 1'b0;
                done  <= 1'b0;
            end
            
            load: begin
                din_reg <= {din, addr, wr};
                state   <= check_op;
            end

            check_op: begin
                if(wr == 1'b1 && addr < 32) begin
                    cs <= 1'b0;
                    state <= send_data;
                end
                else if (wr == 1'b0 && addr < 32) begin
                    state <= read_data1;
                    cs <= 1'b0;
                end
                else begin
                    state <= error;
                    cs <= 1'b1;
                end
            end

            send_data: begin
                if(count <= 16) begin
                    count <= count + 1;
                    mosi  <= din_reg[count];
                    state = send_data;
                end
                else begin
                    cs    <= 1'b1;
                    mosi  <= 1'b0;
                    if(op_done) begin
                        count <= 0;
                        done  <= 1'b1;
                        state <= idle;
                    end
                    else begin
                        state <= send_data;
                    end
                end
            end

            read_data1: begin
                if(count <= 8) begin
                    count <= count + 1;
                    mosi  <= din_reg[count];
                    state <= read_data1;
                end
                else begin
                    count <= 0;
                    cs    <= 1'b1;
                    state <= check_ready;
                end
            end
   
            check_ready: begin
                if(ready)
                    state <= read_data2;
                else
                    state <= check_ready;
            end

            read_data2: begin
                if(count <= 7) begin
                    count <= count + 1;
                    dout_reg[count] <= miso;
                    state = read_data2;
                end
                else begin
                    count <= 0;
                    done <= 1'b1;
                    state <= idle;
                end
            end
            
            error: begin
                err   <= 1'b1;
                state <= idle;
                done  <= 1'b1;
            end
            
            default: begin
                state <= idle;
                count <= 0;
            end
        endcase
    end 
end 


assign dout = dout_reg;
endmodule

module spi_mem(
    input clk, rst, cs, mosi,
    output reg ready, miso, op_done
);

reg [7:0] mem [31:0];
integer i;
initial begin
    for (i=0; i<32; i=i+1) mem[i] = 8'd0;
end
integer count = 0;
reg [15:0] datain;
reg [7:0]  dataout;

typedef enum bit [2:0] {idle = 0, detect = 1, store = 2, send_addr = 3, send_data = 4} state_type;
state_type state = idle;

always@(posedge clk) begin
    if(rst) begin
        state <= idle;
        count <= 0;
        miso  <= 0;
        ready <= 0;
        op_done <= 0;
        datain <= 0;
        dataout <= 0;
    end
    else begin
        case(state)
            idle: begin
                count <= 0;
                miso  <= 0;
                ready <= 0;
                op_done <= 0;
                datain <= 0;
                if(!cs)
                    state <= detect;
                else
                    state <= idle;
            end
              
            detect: begin 
                if(mosi)
                    state <= store; ///write in slave
                else
                    state <= send_addr;   ///read from slave
            end
               
            store: begin
                if(count <= 15) begin
                    datain[count] <= mosi;
                    count         <= count + 1;
                    state         <= store;
                end
                else begin
                    mem[datain[7:0]] <= datain[15:8];
                    state <= idle;
                    count <= 0;
                    op_done <= 1'b1;
                end
            end
                
            send_addr: begin
                if(count <= 7) begin
                    count <= count + 1;
                    datain[count] <= mosi;
                    state <= send_addr;
                end
                else begin
                    count <= 0;
                    state <= send_data;
                    ready <= 1'b1;
                    dataout <= mem[datain];
                end
            end
                   
            send_data: begin
                ready <= 1'b0;
                if(count < 8) begin
                    count <= count + 1;
                    miso  <= dataout[count]; 
                    state <= send_data;
                end 
                else begin
                    count <= 0;
                    state <= idle;
                    op_done <= 1'b1;
                end     
            end   
                
            default: state <= idle;
        endcase
    end
end
endmodule

module top(
    input wr,clk,rst,
    input [7:0] addr, din,
    output [7:0] dout,
    output done, err
);
wire csreg, mosireg, misoreg, readyreg, opdonereg;

spi_intf intf (wr, clk, rst, readyreg, opdonereg, addr, din, dout, csreg, mosireg, misoreg, done, err);
spi_mem  mem_inst (clk, rst, csreg, mosireg, readyreg, misoreg, opdonereg);

endmodule

interface spi_i;
  
    logic wr,clk,rst;
    logic [7:0] addr, din;
    logic [7:0] dout;
    logic done, err;
  
endinterface

sim/dump.vcd
$date
	Fri Jul  3 13:59:26 2026
$end
$version
	Icarus Verilog
$end
$timescale
	1ps
$end
$scope module top $end
$var wire 8 ! addr [7:0] $end
$var wire 1 " clk $end
$var wire 8 # din [7:0] $end
$var wire 1 $ rst $end
$var wire 1 % wr $end
$var wire 1 & readyreg $end
$var wire 1 ' opdonereg $end
$var wire 1 ( mosireg $end
$var wire 1 ) misoreg $end
$var wire 1 * err $end
$var wire 8 + dout [7:0] $end
$var wire 1 , done $end
$var wire 1 - csreg $end
$scope module intf $end
$var wire 8 . addr [7:0] $end
$var wire 1 " clk $end
$var wire 8 / din [7:0] $end
$var wire 8 0 dout [7:0] $end
$var wire 1 $ rst $end
$var wire 1 % wr $end
$var wire 1 & ready $end
$var wire 1 ' op_done $end
$var wire 1 ) miso $end
$var reg 1 - cs $end
$var reg 17 1 din_reg [16:0] $end
$var reg 1 , done $end
$var reg 8 2 dout_reg [7:0] $end
$var reg 1 * err $end
$var reg 1 ( mosi $end
$var integer 32 3 count [31:0] $end
$var reg 3 4 state [2:0] $end
$upscope $end
$scope module mem_inst $end
$var wire 1 " clk $end
$var wire 1 - cs $end
$var wire 1 ( mosi $end
$var wire 1 $ rst $end
$var reg 16 5 datain [15:0] $end
$var reg 8 6 dataout [7:0] $end
$var reg 1 ) miso $end
$var reg 1 ' op_done $end
$var reg 1 & ready $end
$var integer 32 7 count [31:0] $end
$var integer 32 8 i [31:0] $end
$var reg 3 9 state [2:0] $end
$upscope $end
$upscope $end
$enddefinitions $end
$comment Show the parameter values. $end
$dumpall
$end
#0
$dumpvars
b0 9
b100000 8
b0 7
b0 6
b0 5
b0 4
b0 3
b0 2
b0 1
b0 0
b0 /
b0 .
1-
0,
b0 +
0*
0)
0(
0'
0&
0%
1$
b0 #
1"
b0 !
$end
#5000
0"
#10000
1"
#15000
0"
#20000
1"
#25000
0"
#30000
1"
#35000
0"
#40000
b11100001 #
b11100001 /
b10 !
b10 .
1%
0$
1"
#45000
0"
#50000
b1 4
1"
#55000
0"
#60000
b10 4
b11100001000000101 1
1"
#65000
0"
#70000
b11 4
0-
1"
#75000
0"
#80000
1(
b1 3
b1 9
1"
#85000
0"
#90000
b10 9
0(
b10 3
1"
#95000
0"
#100000
1(
b11 3
b1 7
1"
#105000
0"
#110000
b10 7
b10 5
0(
b100 3
1"
#115000
0"
#120000
b101 3
b11 7
1"
#125000
0"
#130000
b100 7
b110 3
1"
#135000
0"
#140000
b111 3
b101 7
1"
#145000
0"
#150000
b110 7
b1000 3
1"
#155000
0"
#160000
b1001 3
b111 7
1"
#165000
0"
#170000
b1000 7
1(
b1010 3
1"
#175000
0"
#180000
0(
b1011 3
b1001 7
b100000010 5
1"
#185000
0"
#190000
b1010 7
b1100 3
1"
#195000
0"
#200000
b1101 3
b1011 7
1"
#205000
0"
#210000
b1100 7
b1110 3
1"
#215000
0"
#220000
1(
b1111 3
b1101 7
1"
#225000
0"
#230000
b1110 7
b10000100000010 5
b10000 3
1"
#235000
0"
#240000
b10001 3
b1111 7
b110000100000010 5
1"
#245000
0"
#250000
b10000 7
b1110000100000010 5
0(
1-
1"
#255000
0"
#260000
1'
b0 7
b0 9
1"
#265000
0"
#270000
b101010 #
b101010 /
b110 !
b110 .
b0 5
0'
b0 4
1,
b0 3
1"
#275000
0"
#280000
0,
b1 4
1"
#285000
0"
#290000
b10 4
b101010000001101 1
1"
#295000
0"
#300000
b11 4
0-
1"
#305000
0"
#310000
b1 9
1(
b1 3
1"
#315000
0"
#320000
0(
b10 3
b10 9
1"
#325000
0"
#330000
b1 7
1(
b11 3
1"
#335000
0"
#340000
b100 3
b10 7
b10 5
1"
#345000
0"
#350000
b11 7
b110 5
0(
b101 3
1"
#355000
0"
#360000
b110 3
b100 7
1"
#365000
0"
#370000
b101 7
b111 3
1"
#375000
0"
#380000
b1000 3
b110 7
1"
#385000
0"
#390000
b111 7
b1001 3
1"
#395000
0"
#400000
b1010 3
b1000 7
1"
#405000
0"
#410000
b1001 7
1(
b1011 3
1"
#415000
0"
#420000
0(
b1100 3
b1010 7
b1000000110 5
1"
#425000
0"
#430000
b1011 7
1(
b1101 3
1"
#435000
0"
#440000
0(
b1110 3
b1100 7
b101000000110 5
1"
#445000
0"
#450000
b1101 7
1(
b1111 3
1"
#455000
0"
#460000
0(
b10000 3
b1110 7
b10101000000110 5
1"
#465000
0"
#470000
b1111 7
b10001 3
1"
#475000
0"
#480000
1-
b10000 7
1"
#485000
0"
#490000
1'
b0 7
b0 9
1"
#495000
0"
#500000
b10101001 #
b10101001 /
b1001 !
b1001 .
b0 4
1,
b0 3
b0 5
0'
1"
#505000
0"
#510000
0,
b1 4
1"
#515000
0"
#520000
b10 4
b10101001000010011 1
1"
#525000
0"
#530000
b11 4
0-
1"
#535000
0"
#540000
1(
b1 3
b1 9
1"
#545000
0"
#550000
b10 9
b10 3
1"
#555000
0"
#560000
0(
b11 3
b1 7
b1 5
1"
#565000
0"
#570000
b10 7
b100 3
1"
#575000
0"
#580000
1(
b101 3
b11 7
1"
#585000
0"
#590000
b100 7
b1001 5
0(
b110 3
1"
#595000
0"
#600000
b111 3
b101 7
1"
#605000
0"
#610000
b110 7
b1000 3
1"
#615000
0"
#620000
b1001 3
b111 7
1"
#625000
0"
#630000
b1000 7
1(
b1010 3
1"
#635000
0"
#640000
0(
b1011 3
b1001 7
b100001001 5
1"
#645000
0"
#650000
b1010 7
b1100 3
1"
#655000
0"
#660000
1(
b1101 3
b1011 7
1"
#665000
0"
#670000
b1100 7
b100100001001 5
0(
b1110 3
1"
#675000
0"
#680000
1(
b1111 3
b1101 7
1"
#685000
0"
#690000
b1110 7
b10100100001001 5
0(
b10000 3
1"
#695000
0"
#700000
1(
b10001 3
b1111 7
1"
#705000
0"
#710000
b10000 7
b1010100100001001 5
0(
1-
1"
#715000
0"
#720000
1'
b0 7
b0 9
1"
#725000
0"
#730000
b11100011 #
b11100011 /
b10 !
b10 .
b0 5
0'
b0 4
1,
b0 3
1"
#735000
0"
#740000
0,
b1 4
1"
#745000
0"
#750000
b10 4
b11100011000000101 1
1"
#755000
0"
#760000
b11 4
0-
1"
#765000
0"
#770000
b1 9
1(
b1 3
1"
#775000
0"
#780000
0(
b10 3
b10 9
1"
#785000
0"
#790000
b1 7
1(
b11 3
1"
#795000
0"
#800000
0(
b100 3
b10 7
b10 5
1"
#805000
0"
#810000
b11 7
b101 3
1"
#815000
0"
#820000
b110 3
b100 7
1"
#825000
0"
#830000
b101 7
b111 3
1"
#835000
0"
#840000
b1000 3
b110 7
1"
#845000
0"
#850000
b111 7
b1001 3
1"
#855000
0"
#860000
1(
b1010 3
b1000 7
1"
#865000
0"
#870000
b1001 7
b100000010 5
b1011 3
1"
#875000
0"
#880000
0(
b1100 3
b1010 7
b1100000010 5
1"
#885000
0"
#890000
b1011 7
b1101 3
1"
#895000
0"
#900000
b1110 3
b1100 7
1"
#905000
0"
#910000
b1101 7
1(
b1111 3
1"
#915000
0"
#920000
b10000 3
b1110 7
b10001100000010 5
1"
#925000
0"
#930000
b1111 7
b110001100000010 5
b10001 3
1"
#935000
0"
#940000
0(
1-
b10000 7
b1110001100000010 5
1"
#945000
0"
#950000
1'
b0 7
b0 9
1"
#955000
0"
#960000
b1101111 #
b1101111 /
b110 !
b110 .
b0 4
1,
b0 3
b0 5
0'
1"
#965000
0"
#970000
0,
b1 4
1"
#975000
0"
#980000
b10 4
b1101111000001101 1
1"
#985000
0"
#990000
b11 4
0-
1"
#995000
0"
#1000000
1(
b1 3
b1 9
1"
#1005000
0"
#1010000
b10 9
0(
b10 3
1"
#1015000
0"
#1020000
1(
b11 3
b1 7
1"
#1025000
0"
#1030000
b10 7
b10 5
b100 3
1"
#1035000
0"
#1040000
0(
b101 3
b11 7
b110 5
1"
#1045000
0"
#1050000
b100 7
b110 3
1"
#1055000
0"
#1060000
b111 3
b101 7
1"
#1065000
0"
#1070000
b110 7
b1000 3
1"
#1075000
0"
#1080000
b1001 3
b111 7
1"
#1085000
0"
#1090000
b1000 7
1(
b1010 3
1"
#1095000
0"
#1100000
b1011 3
b1001 7
b100000110 5
1"
#1105000
0"
#1110000
b1010 7
b1100000110 5
b1100 3
1"
#1115000
0"
#1120000
b1101 3
b1011 7
b11100000110 5
1"
#1125000
0"
#1130000
b1100 7
b111100000110 5
0(
b1110 3
1"
#1135000
0"
#1140000
1(
b1111 3
b1101 7
1"
#1145000
0"
#1150000
b1110 7
b10111100000110 5
b10000 3
1"
#1155000
0"
#1160000
0(
b10001 3
b1111 7
b110111100000110 5
1"
#1165000
0"
#1170000
b10000 7
1-
1"
#1175000
0"
#1180000
1'
b0 7
b0 9
1"
#1185000
0"
#1190000
b10001010 #
b10001010 /
b1 !
b1 .
b0 5
0'
b0 4
1,
b0 3
1"
#1195000
0"
#1200000
0,
b1 4
1"
#1205000
0"
#1210000
b10 4
b10001010000000011 1
1"
#1215000
0"
#1220000
b11 4
0-
1"
#1225000
0"
#1230000
b1 9
1(
b1 3
1"
#1235000
0"
#1240000
b10 3
b10 9
1"
#1245000
0"
#1250000
b1 7
b1 5
0(
b11 3
1"
#1255000
0"
#1260000
b100 3
b10 7
1"
#1265000
0"
#1270000
b11 7
b101 3
1"
#1275000
0"
#1280000
b110 3
b100 7
1"
#1285000
0"
#1290000
b101 7
b111 3
1"
#1295000
0"
#1300000
b1000 3
b110 7
1"
#1305000
0"
#1310000
b111 7
b1001 3
1"
#1315000
0"
#1320000
b1010 3
b1000 7
1"
#1325000
0"
#1330000
b1001 7
1(
b1011 3
1"
#1335000
0"
#1340000
0(
b1100 3
b1010 7
b1000000001 5
1"
#1345000
0"
#1350000
b1011 7
1(
b1101 3
1"
#1355000
0"
#1360000
0(
b1110 3
b1100 7
b101000000001 5
1"
#1365000
0"
#1370000
b1101 7
b1111 3
1"
#1375000
0"
#1380000
b10000 3
b1110 7
1"
#1385000
0"
#1390000
b1111 7
1(
b10001 3
1"
#1395000
0"
#1400000
0(
1-
b10000 7
b1000101000000001 5
1"
#1405000
0"
#1410000
1'
b0 7
b0 9
1"
#1415000
0"
#1420000
b111011 #
b111011 /
b1001 !
b1001 .
b0 4
1,
b0 3
b0 5
0'
1"
#1425000
0"
#1430000
0,
b1 4
1"
#1435000
0"
#1440000
b10 4
b111011000010011 1
1"
#1445000
0"
#1450000
b11 4
0-
1"
#1455000
0"
#1460000
1(
b1 3
b1 9
1"
#1465000
0"
#1470000
b10 9
b10 3
1"
#1475000
0"
#1480000
0(
b11 3
b1 7
b1 5
1"
#1485000
0"
#1490000
b10 7
b100 3
1"
#1495000
0"
#1500000
1(
b101 3
b11 7
1"
#1505000
0"
#1510000
b100 7
b1001 5
0(
b110 3
1"
#1515000
0"
#1520000
b111 3
b101 7
1"
#1525000
0"
#1530000
b110 7
b1000 3
1"
#1535000
0"
#1540000
b1001 3
b111 7
1"
#1545000
0"
#1550000
b1000 7
1(
b1010 3
1"
#1555000
0"
#1560000
b1011 3
b1001 7
b100001001 5
1"
#1565000
0"
#1570000
b1010 7
b1100001001 5
0(
b1100 3
1"
#1575000
0"
#1580000
1(
b1101 3
b1011 7
1"
#1585000
0"
#1590000
b1100 7
b101100001001 5
b1110 3
1"
#1595000
0"
#1600000
b1111 3
b1101 7
b1101100001001 5
1"
#1605000
0"
#1610000
b1110 7
b11101100001001 5
0(
b10000 3
1"
#1615000
0"
#1620000
b10001 3
b1111 7
1"
#1625000
0"
#1630000
b10000 7
1-
1"
#1635000
0"
#1640000
1'
b0 7
b0 9
1"
#1645000
0"
#1650000
b1011110 #
b1011110 /
b10 !
b10 .
b0 5
0'
b0 4
1,
b0 3
1"
#1655000
0"
#1660000
0,
b1 4
1"
#1665000
0"
#1670000
b10 4
b1011110000000101 1
1"
#1675000
0"
#1680000
b11 4
0-
1"
#1685000
0"
#1690000
b1 9
1(
b1 3
1"
#1695000
0"
#1700000
0(
b10 3
b10 9
1"
#1705000
0"
#1710000
b1 7
1(
b11 3
1"
#1715000
0"
#1720000
0(
b100 3
b10 7
b10 5
1"
#1725000
0"
#1730000
b11 7
b101 3
1"
#1735000
0"
#1740000
b110 3
b100 7
1"
#1745000
0"
#1750000
b101 7
b111 3
1"
#1755000
0"
#1760000
b1000 3
b110 7
1"
#1765000
0"
#1770000
b111 7
b1001 3
1"
#1775000
0"
#1780000
b1010 3
b1000 7
1"
#1785000
0"
#1790000
b1001 7
1(
b1011 3
1"
#1795000
0"
#1800000
b1100 3
b1010 7
b1000000010 5
1"
#1805000
0"
#1810000
b1011 7
b11000000010 5
b1101 3
1"
#1815000
0"
#1820000
b1110 3
b1100 7
b111000000010 5
1"
#1825000
0"
#1830000
b1101 7
b1111000000010 5
0(
b1111 3
1"
#1835000
0"
#1840000
1(
b10000 3
b1110 7
1"
#1845000
0"
#1850000
b1111 7
b101111000000010 5
0(
b10001 3
1"
#1855000
0"
#1860000
1-
b10000 7
1"
#1865000
0"
#1870000
1'
b0 7
b0 9
1"
#1875000
0"
#1880000
b110111 #
b110111 /
b0 4
1,
b0 3
b0 5
0'
1"
#1885000
0"
#1890000
0,
b1 4
1"
#1895000
0"
#1900000
b10 4
b110111000000101 1
1"
#1905000
0"
#1910000
b11 4
0-
1"
#1915000
0"
#1920000
1(
b1 3
b1 9
1"
#1925000
0"
#1930000
b10 9
0(
b10 3
1"
#1935000
0"
#1940000
1(
b11 3
b1 7
1"
#1945000
0"
#1950000
b10 7
b10 5
0(
b100 3
1"
#1955000
0"
#1960000
b101 3
b11 7
1"
#1965000
0"
#1970000
b100 7
b110 3
1"
#1975000
0"
#1980000
b111 3
b101 7
1"
#1985000
0"
#1990000
b110 7
b1000 3
1"
#1995000
0"
#2000000
b1001 3
b111 7
1"
#2005000
0"
#2010000
b1000 7
1(
b1010 3
1"
#2015000
0"
#2020000
b1011 3
b1001 7
b100000010 5
1"
#2025000
0"
#2030000
b1010 7
b1100000010 5
b1100 3
1"
#2035000
0"
#2040000
0(
b1101 3
b1011 7
b11100000010 5
1"
#2045000
0"
#2050000
b1100 7
1(
b1110 3
1"
#2055000
0"
#2060000
b1111 3
b1101 7
b1011100000010 5
1"
#2065000
0"
#2070000
b1110 7
b11011100000010 5
0(
b10000 3
1"
#2075000
0"
#2080000
b10001 3
b1111 7
1"
#2085000
0"
#2090000
b10000 7
1-
1"
#2095000
0"
#2100000
1'
b0 7
b0 9
1"
#2105000
0"
#2110000
b1100100 #
b1100100 /
b11 !
b11 .
b0 5
0'
b0 4
1,
b0 3
1"
#2115000
0"
#2120000
0,
b1 4
1"
#2125000
0"
#2130000
b10 4
b1100100000000111 1
1"
#2135000
0"
#2140000
b11 4
0-
1"
#2145000
0"
#2150000
b1 9
1(
b1 3
1"
#2155000
0"
#2160000
b10 3
b10 9
1"
#2165000
0"
#2170000
b1 7
b1 5
b11 3
1"
#2175000
0"
#2180000
0(
b100 3
b10 7
b11 5
1"
#2185000
0"
#2190000
b11 7
b101 3
1"
#2195000
0"
#2200000
b110 3
b100 7
1"
#2205000
0"
#2210000
b101 7
b111 3
1"
#2215000
0"
#2220000
b1000 3
b110 7
1"
#2225000
0"
#2230000
b111 7
b1001 3
1"
#2235000
0"
#2240000
b1010 3
b1000 7
1"
#2245000
0"
#2250000
b1001 7
b1011 3
1"
#2255000
0"
#2260000
1(
b1100 3
b1010 7
1"
#2265000
0"
#2270000
b1011 7
b10000000011 5
0(
b1101 3
1"
#2275000
0"
#2280000
b1110 3
b1100 7
1"
#2285000
0"
#2290000
b1101 7
1(
b1111 3
1"
#2295000
0"
#2300000
b10000 3
b1110 7
b10010000000011 5
1"
#2305000
0"
#2310000
b1111 7
b110010000000011 5
0(
b10001 3
1"
#2315000
0"
#2320000
1-
b10000 7
1"
#2325000
0"
#2330000
1'
b0 7
b0 9
1"
#2335000
0"
#2340000
b11001111 #
b11001111 /
b1 !
b1 .
0%
b0 4
1,
b0 3
b0 5
0'
1"
#2345000
0"
#2350000
0,
b1 4
1"
#2355000
0"
#2360000
b10 4
b11001111000000010 1
1"
#2365000
0"
#2370000
0-
b100 4
1"
#2375000
0"
#2380000
b1 3
b1 9
1"
#2385000
0"
#2390000
b11 9
1(
b10 3
1"
#2395000
0"
#2400000
0(
b11 3
b1 5
b1 7
1"
#2405000
0"
#2410000
b10 7
b100 3
1"
#2415000
0"
#2420000
b101 3
b11 7
1"
#2425000
0"
#2430000
b100 7
b110 3
1"
#2435000
0"
#2440000
b111 3
b101 7
1"
#2445000
0"
#2450000
b110 7
b1000 3
1"
#2455000
0"
#2460000
b1001 3
b111 7
1"
#2465000
0"
#2470000
b1000 7
b111 4
1-
b0 3
1"
#2475000
0"
#2480000
b10001010 6
1&
b100 9
b0 7
1"
#2485000
0"
#2490000
b1 7
0&
b101 4
1"
#2495000
0"
#2500000
b1 3
1)
b10 7
1"
#2505000
0"
#2510000
0)
b11 7
b10 +
b10 0
b10 2
b10 3
1"
#2515000
0"
#2520000
b11 3
1)
b100 7
1"
#2525000
0"
#2530000
0)
b101 7
b1010 +
b1010 0
b1010 2
b100 3
1"
#2535000
0"
#2540000
b101 3
b110 7
1"
#2545000
0"
#2550000
b111 7
b110 3
1"
#2555000
0"
#2560000
b111 3
1)
b1000 7
1"
#2565000
0"
#2570000
1'
b0 9
b0 7
b10001010 +
b10001010 0
b10001010 2
b1000 3
1"
#2575000
0"
#2580000
b11010011 #
b11010011 /
b10 !
b10 .
b0 4
1,
b0 3
b0 5
0'
0)
1"
#2585000
0"
#2590000
0,
b1 4
1"
#2595000
0"
#2600000
b10 4
b11010011000000100 1
1"
#2605000
0"
#2610000
0-
b100 4
1"
#2615000
0"
#2620000
b1 3
b1 9
1"
#2625000
0"
#2630000
b11 9
b10 3
1"
#2635000
0"
#2640000
1(
b11 3
b1 7
1"
#2645000
0"
#2650000
b10 5
b10 7
0(
b100 3
1"
#2655000
0"
#2660000
b101 3
b11 7
1"
#2665000
0"
#2670000
b100 7
b110 3
1"
#2675000
0"
#2680000
b111 3
b101 7
1"
#2685000
0"
#2690000
b110 7
b1000 3
1"
#2695000
0"
#2700000
b1001 3
b111 7
1"
#2705000
0"
#2710000
b1000 7
b111 4
1-
b0 3
1"
#2715000
0"
#2720000
b110111 6
1&
b100 9
b0 7
1"
#2725000
0"
#2730000
1)
b1 7
0&
b101 4
1"
#2735000
0"
#2740000
b10001011 +
b10001011 0
b10001011 2
b1 3
b10 7
1"
#2745000
0"
#2750000
b11 7
b10 3
1"
#2755000
0"
#2760000
b10001111 +
b10001111 0
b10001111 2
b11 3
0)
b100 7
1"
#2765000
0"
#2770000
1)
b101 7
b10000111 +
b10000111 0
b10000111 2
b100 3
1"
#2775000
0"
#2780000
b10010111 +
b10010111 0
b10010111 2
b101 3
b110 7
1"
#2785000
0"
#2790000
0)
b111 7
b10110111 +
b10110111 0
b10110111 2
b110 3
1"
#2795000
0"
#2800000
b111 3
b1000 7
1"
#2805000
0"
#2810000
1'
b0 9
b0 7
b110111 +
b110111 0
b110111 2
b1000 3
1"
#2815000
0"
#2820000
b10101111 #
b10101111 /
b111 !
b111 .
b0 4
1,
b0 3
b0 5
0'
1"
#2825000
0"
#2830000
0,
b1 4
1"
#2835000
0"
#2840000
b10 4
b10101111000001110 1
1"
#2845000
0"
#2850000
0-
b100 4
1"
#2855000
0"
#2860000
b1 3
b1 9
1"
#2865000
0"
#2870000
b11 9
1(
b10 3
1"
#2875000
0"
#2880000
b11 3
b1 5
b1 7
1"
#2885000
0"
#2890000
b11 5
b10 7
b100 3
1"
#2895000
0"
#2900000
0(
b101 3
b111 5
b11 7
1"
#2905000
0"
#2910000
b100 7
b110 3
1"
#2915000
0"
#2920000
b111 3
b101 7
1"
#2925000
0"
#2930000
b110 7
b1000 3
1"
#2935000
0"
#2940000
b1001 3
b111 7
1"
#2945000
0"
#2950000
b1000 7
b111 4
1-
b0 3
1"
#2955000
0"
#2960000
b0 6
1&
b100 9
b0 7
1"
#2965000
0"
#2970000
b1 7
0&
b101 4
1"
#2975000
0"
#2980000
b110110 +
b110110 0
b110110 2
b1 3
b10 7
1"
#2985000
0"
#2990000
b11 7
b110100 +
b110100 0
b110100 2
b10 3
1"
#2995000
0"
#3000000
b110000 +
b110000 0
b110000 2
b11 3
b100 7
1"
#3005000
0"
#3010000
b101 7
b100 3
1"
#3015000
0"
#3020000
b100000 +
b100000 0
b100000 2
b101 3
b110 7
1"
#3025000
0"
#3030000
b111 7
b0 +
b0 0
b0 2
b110 3
1"
#3035000
0"
#3040000
b111 3
b1000 7
1"
#3045000
0"
#3050000
1'
b0 9
b0 7
b1000 3
1"
#3055000
0"
#3060000
b1010110 #
b1010110 /
b1001 !
b1001 .
b0 4
1,
b0 3
b0 5
0'
1"
#3065000
0"
#3070000
0,
b1 4
1"
#3075000
0"
#3080000
b10 4
b1010110000010010 1
1"
#3085000
0"
#3090000
0-
b100 4
1"
#3095000
0"
#3100000
b1 3
b1 9
1"
#3105000
0"
#3110000
b11 9
1(
b10 3
1"
#3115000
0"
#3120000
0(
b11 3
b1 5
b1 7
1"
#3125000
0"
#3130000
b10 7
b100 3
1"
#3135000
0"
#3140000
1(
b101 3
b11 7
1"
#3145000
0"
#3150000
b1001 5
b100 7
0(
b110 3
1"
#3155000
0"
#3160000
b111 3
b101 7
1"
#3165000
0"
#3170000
b110 7
b1000 3
1"
#3175000
0"
#3180000
b1001 3
b111 7
1"
#3185000
0"
#3190000
b1000 7
b111 4
1-
b0 3
1"
#3195000
0"
#3200000
b111011 6
1&
b100 9
b0 7
1"
#3205000
0"
#3210000
1)
b1 7
0&
b101 4
1"
#3215000
0"
#3220000
b1 +
b1 0
b1 2
b1 3
b10 7
1"
#3225000
0"
#3230000
0)
b11 7
b11 +
b11 0
b11 2
b10 3
1"
#3235000
0"
#3240000
b11 3
1)
b100 7
1"
#3245000
0"
#3250000
b101 7
b1011 +
b1011 0
b1011 2
b100 3
1"
#3255000
0"
#3260000
b11011 +
b11011 0
b11011 2
b101 3
b110 7
1"
#3265000
0"
#3270000
0)
b111 7
b111011 +
b111011 0
b111011 2
b110 3
1"
#3275000
0"
#3280000
b111 3
b1000 7
1"
#3285000
0"
#3290000
1'
b0 9
b0 7
b1000 3
1"
#3295000
0"
#3300000
b1110000 #
b1110000 /
b1010 !
b1010 .
b0 4
1,
b0 3
b0 5
0'
1"
#3305000
0"
#3310000
0,
b1 4
1"
#3315000
0"
#3320000
b10 4
b1110000000010100 1
1"
#3325000
0"
#3330000
0-
b100 4
1"
#3335000
0"
#3340000
b1 3
b1 9
1"
#3345000
0"
#3350000
b11 9
b10 3
1"
#3355000
0"
#3360000
1(
b11 3
b1 7
1"
#3365000
0"
#3370000
b10 5
b10 7
0(
b100 3
1"
#3375000
0"
#3380000
1(
b101 3
b11 7
1"
#3385000
0"
#3390000
b1010 5
b100 7
0(
b110 3
1"
#3395000
0"
#3400000
b111 3
b101 7
1"
#3405000
0"
#3410000
b110 7
b1000 3
1"
#3415000
0"
#3420000
b1001 3
b111 7
1"
#3425000
0"
#3430000
b1000 7
b111 4
1-
b0 3
1"
#3435000
0"
#3440000
b0 6
1&
b100 9
b0 7
1"
#3445000
0"
#3450000
b1 7
0&
b101 4
1"
#3455000
0"
#3460000
b111010 +
b111010 0
b111010 2
b1 3
b10 7
1"
#3465000
0"
#3470000
b11 7
b111000 +
b111000 0
b111000 2
b10 3
1"
#3475000
0"
#3480000
b11 3
b100 7
1"
#3485000
0"
#3490000
b101 7
b110000 +
b110000 0
b110000 2
b100 3
1"
#3495000
0"
#3500000
b100000 +
b100000 0
b100000 2
b101 3
b110 7
1"
#3505000
0"
#3510000
b111 7
b0 +
b0 0
b0 2
b110 3
1"
#3515000
0"
#3520000
b111 3
b1000 7
1"
#3525000
0"
#3530000
1'
b0 9
b0 7
b1000 3
1"
#3535000
0"
#3540000
b1010010 #
b1010010 /
b10 !
b10 .
b0 4
1,
b0 3
b0 5
0'
1"
#3545000
0"
#3550000
0,
b1 4
1"
#3555000
0"
#3560000
b10 4
b1010010000000100 1
1"
#3565000
0"
#3570000
0-
b100 4
1"
#3575000
0"
#3580000
b1 3
b1 9
1"
#3585000
0"
#3590000
b11 9
b10 3
1"
#3595000
0"
#3600000
1(
b11 3
b1 7
1"
#3605000
0"
#3610000
b10 5
b10 7
0(
b100 3
1"
#3615000
0"
#3620000
b101 3
b11 7
1"
#3625000
0"
#3630000
b100 7
b110 3
1"
#3635000
0"
#3640000
b111 3
b101 7
1"
#3645000
0"
#3650000
b110 7
b1000 3
1"
#3655000
0"
#3660000
b1001 3
b111 7
1"
#3665000
0"
#3670000
b1000 7
b111 4
1-
b0 3
1"
#3675000
0"
#3680000
b110111 6
1&
b100 9
b0 7
1"
#3685000
0"
#3690000
1)
b1 7
0&
b101 4
1"
#3695000
0"
#3700000
b1 +
b1 0
b1 2
b1 3
b10 7
1"
#3705000
0"
#3710000
b11 7
b11 +
b11 0
b11 2
b10 3
1"
#3715000
0"
#3720000
b111 +
b111 0
b111 2
b11 3
0)
b100 7
1"
#3725000
0"
#3730000
1)
b101 7
b100 3
1"
#3735000
0"
#3740000
b10111 +
b10111 0
b10111 2
b101 3
b110 7
1"
#3745000
0"
#3750000
0)
b111 7
b110111 +
b110111 0
b110111 2
b110 3
1"
#3755000
0"
#3760000
b111 3
b1000 7
1"
#3765000
0"
